SimpleFacturaSDK/__init__.py
SimpleFacturaSDK/client_simple_factura.py
SimpleFacturaSDK/log.png
SimpleFacturaSDK/main.py
SimpleFacturaSDK/Utilidades/EnviarArchivoFacturacionMasiva.py
SimpleFacturaSDK/Utilidades/Simplificar_error.py
SimpleFacturaSDK/Utilidades/Utilidades.py
SimpleFacturaSDK/Utilidades/__init__.py
SimpleFacturaSDK/Utilidades/auth_utils.py
SimpleFacturaSDK/enumeracion/Ambiente.py
SimpleFacturaSDK/enumeracion/CodigosAduana.py
SimpleFacturaSDK/enumeracion/FormaPago.py
SimpleFacturaSDK/enumeracion/IndicadorExento.py
SimpleFacturaSDK/enumeracion/IndicadorFacturacionExencion.py
SimpleFacturaSDK/enumeracion/IndicadorServicio.py
SimpleFacturaSDK/enumeracion/MedioPago.py
SimpleFacturaSDK/enumeracion/ReasonTypeEnum.py
SimpleFacturaSDK/enumeracion/RejectionType.py
SimpleFacturaSDK/enumeracion/ResponseType.py
SimpleFacturaSDK/enumeracion/TipoCuentaPago.py
SimpleFacturaSDK/enumeracion/TipoDTE.py
SimpleFacturaSDK/enumeracion/TipoDescuento.py
SimpleFacturaSDK/enumeracion/TipoDespacho.py
SimpleFacturaSDK/enumeracion/TipoImpresion.py
SimpleFacturaSDK/enumeracion/TipoImpuesto.py
SimpleFacturaSDK/enumeracion/TipoMovimiento.py
SimpleFacturaSDK/enumeracion/TipoRecargoComision.py
SimpleFacturaSDK/enumeracion/TipoReferencia.py
SimpleFacturaSDK/enumeracion/TipoSalida.py
SimpleFacturaSDK/enumeracion/TipoSobreEnvio.py
SimpleFacturaSDK/enumeracion/TipoTraslado.py
SimpleFacturaSDK/enumeracion/__init__.py
SimpleFacturaSDK/examples/Bloletas de Honorarios/ListadoBHEEmitidas.py
SimpleFacturaSDK/examples/Bloletas de Honorarios/ListadoBHERecibidas.py
SimpleFacturaSDK/examples/Bloletas de Honorarios/ObtenerPDFEmitidas.py
SimpleFacturaSDK/examples/Bloletas de Honorarios/ObtenerPDFRecibidas.py
SimpleFacturaSDK/examples/Clientes/CrearClientes.py
SimpleFacturaSDK/examples/Clientes/ListarClientes.py
SimpleFacturaSDK/examples/Clientes/ObtenerDatosCliente.py
SimpleFacturaSDK/examples/Configuracion/DatosEmpresa.py
SimpleFacturaSDK/examples/Facturacion/CederFactura.py
SimpleFacturaSDK-1.1.9.dist-info/LICENSE
SimpleFacturaSDK-1.1.9.dist-info/METADATA
SimpleFacturaSDK-1.1.9.dist-info/WHEEL
SimpleFacturaSDK-1.1.9.dist-info/top_level.txt
SimpleFacturaSDK-1.1.9.dist-info/RECORD
