Metadata-Version: 2.1
Name: SimpleFacturaSDK
Version: 1.1.9
Summary: SDK para la integración con los servicios de SimpleFactura
Home-page: https://github.com/pereacarlos/SimpleFacturaSDK-python
Author: Carlos Perea
Author-email: Carlos Perea <pereacarlos685@gmail.com>
License: MIT
Keywords: dte,factura,boleta,impuestos internos,factura electrónica,boleta electrónica,documento,iva,SII,documento tributario electrónico
Classifier: Programming Language :: Python :: 3
Classifier: License :: OSI Approved :: MIT License
Classifier: Operating System :: OS Independent
Requires-Python: >=3.6
License-File: LICENSE
Requires-Dist: aiohttp
Requires-Dist: requests-toolbelt
Requires-Dist: pydantic
Requires-Dist: httpx
Requires-Dist: requests
Requires-Dist: python-dotenv
Requires-Dist: aiofiles
Provides-Extra: test
Requires-Dist: pytest; extra == "test"
Requires-Dist: pytest-asyncio; extra == "test"
Requires-Dist: requests-mock; extra == "test"
